dc_qiskit_qml/__init__.py
dc_qiskit_qml/_version.py
dc_qiskit_qml/distance_based/__init__.py
dc_qiskit_qml/distance_based/hadamard/_QmlHadamardNeighborClassifier.py
dc_qiskit_qml/distance_based/hadamard/__init__.py
dc_qiskit_qml/distance_based/hadamard/state/_QmlBinaryDataStateCircuitBuilder.py
dc_qiskit_qml/distance_based/hadamard/state/_QmlGenericStateCircuitBuilder.py
dc_qiskit_qml/distance_based/hadamard/state/_QmlStateCircuitBuilder.py
dc_qiskit_qml/distance_based/hadamard/state/__init__.py
dc_qiskit_qml/distance_based/hadamard/state/cnot/_CCXFactory.py
dc_qiskit_qml/distance_based/hadamard/state/cnot/_CCXMöttönen.py
dc_qiskit_qml/distance_based/hadamard/state/cnot/_CCXToffoli.py
dc_qiskit_qml/distance_based/hadamard/state/cnot/__init__.py
dc_qiskit_qml/distance_based/hadamard/state/sparsevector/_MöttönenStatePreparation.py
dc_qiskit_qml/distance_based/hadamard/state/sparsevector/_QiskitNativeStatePreparation.py
dc_qiskit_qml/distance_based/hadamard/state/sparsevector/_QmlFFQramStatePreparation.py
dc_qiskit_qml/distance_based/hadamard/state/sparsevector/_QmlSparseVectorStatePreparation.py
dc_qiskit_qml/distance_based/hadamard/state/sparsevector/__init__.py
dc_qiskit_qml/feature_maps/_FeatureMap.py
dc_qiskit_qml/feature_maps/_FixedLengthQubitEncoding.py
dc_qiskit_qml/feature_maps/_Float32QubitEncoding.py
dc_qiskit_qml/feature_maps/_IdentityFeatureMap.py
dc_qiskit_qml/feature_maps/_NormedAmplitudeEncoding.py
dc_qiskit_qml/feature_maps/__init__.py
dc_qiskit_qml-0.0.3.dist-info/LICENSE
dc_qiskit_qml-0.0.3.dist-info/METADATA
dc_qiskit_qml-0.0.3.dist-info/WHEEL
dc_qiskit_qml-0.0.3.dist-info/top_level.txt
dc_qiskit_qml-0.0.3.dist-info/RECORD
