Metadata-Version: 2.1
Name: dc-qiskit-qml
Version: 0.0.3
Summary: Machine learning (quantum-)algorithms with qiskit as basis
Home-page: http://data-cybernetics.com
Maintainer: Carsten Blank
Maintainer-email: blank@data-cybernetics.com
License: Apache License 2.0
Platform: UNKNOWN
Classifier: Development Status :: 4 - Beta
Classifier: Environment :: Console
Classifier: Intended Audience :: Science/Research
Classifier: License :: OSI Approved :: Apache Software License
Classifier: Natural Language :: English
Classifier: Operating System :: POSIX
Classifier: Operating System :: MacOS :: MacOS X
Classifier: Operating System :: POSIX :: Linux
Classifier: Operating System :: Microsoft :: Windows
Classifier: Programming Language :: Python
Classifier: Programming Language :: Python :: 3
Classifier: Programming Language :: Python :: 3.5
Classifier: Programming Language :: Python :: 3.6
Classifier: Programming Language :: Python :: 3.7
Classifier: Programming Language :: Python :: 3 :: Only
Classifier: Topic :: Scientific/Engineering :: Physics
Provides: dc_qiskit_algorithms
Requires-Dist: qiskit
Requires-Dist: numpy
Requires-Dist: scipy
Requires-Dist: bitstring
Requires-Dist: scikit-learn
Requires-Dist: dc-qiskit-algorithms
